{
  "db_name": "PostgreSQL",
  "query": "SELECT slug, owner_username FROM projects WHERE embed_token = $1",
  "describe": {
    "columns": [
      {
        "ordinal": 0,
        "name": "slug",
        "type_info": "Text"
      },
      {
        "ordinal": 1,
        "name": "owner_username",
        "type_info": "Text"
      }
    ],
    "parameters": {
      "Left": [
        "Text"
      ]
    },
    "nullable": [
      false,
      false
    ]
  },
  "hash": "22020954d4903e012ede17f1539309a4eb868333a0a46c4a9555dd931632de21"
}
